odoo/addons/helpdesk_mgmt_fieldservice_equipment_warranty/README.rst
odoo/addons/helpdesk_mgmt_fieldservice_equipment_warranty/__init__.py
odoo/addons/helpdesk_mgmt_fieldservice_equipment_warranty/__manifest__.py
odoo/addons/helpdesk_mgmt_fieldservice_equipment_warranty/i18n/helpdesk_mgmt_fieldservice_equipment_warranty.pot
odoo/addons/helpdesk_mgmt_fieldservice_equipment_warranty/i18n/it.po
odoo/addons/helpdesk_mgmt_fieldservice_equipment_warranty/models/__init__.py
odoo/addons/helpdesk_mgmt_fieldservice_equipment_warranty/models/helpdesk_ticket.py
odoo/addons/helpdesk_mgmt_fieldservice_equipment_warranty/readme/CONTRIBUTORS.md
odoo/addons/helpdesk_mgmt_fieldservice_equipment_warranty/readme/DESCRIPTION.md
odoo/addons/helpdesk_mgmt_fieldservice_equipment_warranty/static/description/icon.png
odoo/addons/helpdesk_mgmt_fieldservice_equipment_warranty/static/description/index.html
odoo/addons/helpdesk_mgmt_fieldservice_equipment_warranty/views/helpdesk_ticket.xml
odoo_addon_helpdesk_mgmt_fieldservice_equipment_warranty-18.0.1.0.0.4.dist-info/METADATA
odoo_addon_helpdesk_mgmt_fieldservice_equipment_warranty-18.0.1.0.0.4.dist-info/WHEEL
odoo_addon_helpdesk_mgmt_fieldservice_equipment_warranty-18.0.1.0.0.4.dist-info/top_level.txt
odoo_addon_helpdesk_mgmt_fieldservice_equipment_warranty-18.0.1.0.0.4.dist-info/RECORD
